.gitignore
README.MD
pyproject.toml
setup.py
upload.sh
test/test.md
test/test.py
zfuns/__init__.py
zfuns.egg-info/PKG-INFO
zfuns.egg-info/SOURCES.txt
zfuns.egg-info/dependency_links.txt
zfuns.egg-info/requires.txt
zfuns.egg-info/top_level.txt
zfuns/utils/__init__.py
zfuns/utils/chromosome_names.py
zfuns/utils/execute_windows_task.py
zfuns/utils/mysql_client.py
zfuns/utils/now_formatter.py
zfuns/utils/print_pause.py