Metadata-Version: 2.2
Name: zfuns
Version: 2.0.2
Summary: 个人常用函数库
Home-page: https://github.com/zhenghy/zfuns
Author: Haiyang Zheng
Author-email: wnfdsfy@gmail.com
License: MIT
Keywords: common,function,class
Platform: any
Requires-Dist: pymysql
Requires-Dist: pywinrm
Requires-Dist: sqlalchemy
Dynamic: author
Dynamic: author-email
Dynamic: description
Dynamic: description-content-type
Dynamic: home-page
Dynamic: keywords
Dynamic: license
Dynamic: platform
Dynamic: requires-dist
Dynamic: summary
